<?xml version="1.0" encoding="utf-8" ?>
<Maps>
  <Map id="1">
	<Tiles>
	  00 00 00 00 00 00 00 00 00 00 00 00 00 00
	  00 00 00 00 00 00 00 00 00 00 00 00 00 00
	  00 00 00 00 00 00 00 00 00 00 00 00 00 00
	  00 00 00 00 00 00 00 00 00 00 00 00 00 00
	  00 00 00 00 00 00 00 00 00 00 00 00 00 00
	  00 00 00 00 00 01 00 00 00 00 00 00 00 00
	  00 00 00 00 00 00 00 00 00 00 00 00 00 00
	  00 00 00 00 00 00 00 00 00 00 00 00 00 00
	  00 00 00 00 00 00 00 00 00 00 00 00 00 00
	  00 00 00 00 00 00 00 00 01 00 00 00 00 00
	  00 00 00 00 00 00 00 00 00 00 00 00 00 00
	  00 00 00 00 00 00 00 00 00 00 00 00 00 00
	  00 00 00 00 00 00 00 00 00 00 00 00 00 00
	  00 00 00 00 00 00 00 00 00 00 00 00 00 00
	</Tiles>
	<Doors>
	  <Door x="" y="" toMap="" toX="" toY=""/>
	</Doors>
	<AdjacentMaps>
	  <AdjacentMap dir="W" id="2"/>
	</AdjacentMaps>
	<MonsterPacks>
	  <MonsterPack id="1" x="" y="">
		<Monster id="1"/>
		<Monster id="2"/>
		<Monster id="3"/>
	  </MonsterPack>
	</MonsterPacks>
  </Map>
</Maps>
